cfinversion/__init__.py
cfinversion/continuous/__init__.py
cfinversion/continuous/bohman/__init__.py
cfinversion/continuous/bohman/abstract_bohman_inverter.py
cfinversion/continuous/bohman/bohman_inverters.py
cfinversion/continuous/continuous_inverter.py
cfinversion/continuous/fft_based/__init__.py
cfinversion/continuous/fft_based/fft_inverter.py
cfinversion/continuous/fft_based/naive_gp_inverter.py
cfinversion/distributions/__init__.py
cfinversion/distributions/abstract_distribution.py
cfinversion/distributions/laplace.py
cfinversion/distributions/levy.py
cfinversion/distributions/normal.py
cfinversion/distributions/poisson.py
cfinversion/distributions/sqr_uniform.py
cfinversion/distributions/uniform.py
cfinversion/tools/__init__.py
cfinversion/tools/standardizer.py
cfinversion/tools/validation_tools.py
cfinversion-1.0.1.dist-info/LICENSE
cfinversion-1.0.1.dist-info/METADATA
cfinversion-1.0.1.dist-info/WHEEL
cfinversion-1.0.1.dist-info/RECORD
