Metadata-Version: 2.3
Name: cfinversion
Version: 1.0.1
Summary: A package for characteristic functions inversion.
License: MIT
Author: Liliia Imamutdinova
Requires-Python: >=3.10
Classifier: License :: OSI Approved :: MIT License
Classifier: Programming Language :: Python :: 3
Classifier: Programming Language :: Python :: 3.10
Classifier: Programming Language :: Python :: 3.11
Classifier: Programming Language :: Python :: 3.12
Classifier: Programming Language :: Python :: 3.13
Requires-Dist: numpy (>=2.2.0)
Requires-Dist: scipy (>=1.15.0)
Project-URL: Repository, https://github.com/PySATL/pysatl-cfinversion
